wpt_tools/__init__.py
wpt_tools/analysis.py
wpt_tools/data_classes.py
wpt_tools/load_env.py
wpt_tools/logger.py
wpt_tools/plotter.py
wpt_tools/solver.py
wpt_tools/workflow.py
wpt_tools/cli/main.py
wpt_tools-0.1.8.dist-info/METADATA
wpt_tools-0.1.8.dist-info/WHEEL
wpt_tools-0.1.8.dist-info/entry_points.txt
wpt_tools-0.1.8.dist-info/licenses/LICENSE
wpt_tools-0.1.8.dist-info/RECORD
